README
setup.py
pybhl/__init__.py
pybhl/request.py
pybhl/response.py
pybhl.egg-info/PKG-INFO
pybhl.egg-info/SOURCES.txt
pybhl.egg-info/dependency_links.txt
pybhl.egg-info/requires.txt
pybhl.egg-info/top_level.txt