Metadata-Version: 1.0
Name: pybhl
Version: 0.1
Summary: Interact with the Biodiversity Heritage Library API
Home-page: http://github.com/anarchivist/pybhl
Author: Mark A. Matienzo
Author-email: mark@matienzo.org
License: GPL
Platform: UNKNOWN
Classifier: Intended Audience :: Education
Classifier: Intended Audience :: Developers
Classifier: Intended Audience :: Information Technology
Classifier: Intended Audience :: Science/Research
Classifier: License :: OSI Approved :: GNU General Public License (GPL)
Classifier: Programming Language :: Python
Classifier: Development Status :: 3 - Alpha
